ls_improved/__init__.py
ls_improved/config.py
ls_improved/lsi.py
ls_improved/lsi_content.py
ls_improved/lsi_itemloader.py
ls_improved/lsi_text.py
ls_improved/lsi_visual.py
ls_improved/mkdiri.py
ls_Improved-0.5.1.dist-info/LICENSE
ls_Improved-0.5.1.dist-info/METADATA
ls_Improved-0.5.1.dist-info/WHEEL
ls_Improved-0.5.1.dist-info/entry_points.txt
ls_Improved-0.5.1.dist-info/top_level.txt
ls_Improved-0.5.1.dist-info/RECORD
