Metadata-Version: 2.1
Name: ls-Improved
Version: 0.5.1
Summary: show directory description when ls.
Home-page: https://github.com/ShotaroKataoka/ls-Improved
Author: Shotaro Kataoka
Author-email: shotaro.kata@gmail.com
License: MIT
Keywords: ls,filer,command,mkdir,utils
Platform: UNKNOWN
Classifier: Programming Language :: Python
Classifier: Programming Language :: Python :: 3
Classifier: Programming Language :: Python :: 3.4
Classifier: Programming Language :: Python :: 3.5
Classifier: Programming Language :: Python :: 3.6
Classifier: Programming Language :: Python :: 3.7
Classifier: Programming Language :: Python :: 3.8
Classifier: Programming Language :: Python :: 2
Classifier: Programming Language :: Python :: 2.7
Classifier: License :: OSI Approved :: MIT License
Classifier: Operating System :: OS Independent
Requires-Python: >=2.7
